avnet_scotty-2025.9.data/scripts/scotty
avnet_scotty-2025.9.data/scripts/scotty-data-gen
avnet_scotty-2025.9.data/scripts/scotty-doc-link-checker
avnet_scotty-2025.9.data/scripts/scotty-docker
avnet_scotty-2025.9.data/scripts/scotty-dynamic-matrix
avnet_scotty-2025.9.data/scripts/scotty-layer-coverage
avnet_scotty-2025.9.data/scripts/scotty-oeqa-report-enhancer
avnet_scotty-2025.9.data/scripts/scotty-qa-log-filter
avnet_scotty-2025.9.data/scripts/scotty-runqemu
avnet_scotty-2025.9.data/scripts/scotty-shutdown-check
avnet_scotty-2025.9.data/scripts/scotty-start-vm
avnet_scotty-2025.9.data/scripts/scotty-stop-vm
avnet_scotty-2025.9.data/scripts/scotty-test
avnet_scotty-2025.9.data/scripts/scotty-testreport
avnet_scotty-2025.9.data/scripts/scotty-update-recipes-notification
avnet_scotty-2025.9.data/scripts/scotty_vm_bundle.sh
avnet_scotty-2025.9.data/scripts/scotty_vm_create.sh.template
bumper/__init__.py
bumper/__main__.py
avnet_scotty-2025.9.dist-info/LICENSE
avnet_scotty-2025.9.dist-info/METADATA
avnet_scotty-2025.9.dist-info/WHEEL
avnet_scotty-2025.9.dist-info/entry_points.txt
avnet_scotty-2025.9.dist-info/top_level.txt
avnet_scotty-2025.9.dist-info/RECORD
