Metadata-Version: 2.2
Name: avnet-scotty
Version: 2025.9
Summary: scotty: S(imple)C(ore) O(pen) T(echnology) T(ool for) Y(ou)
Author: Avnet Embedded GmbH
License: GPL-3.0-only
Project-URL: Documentation, https://simple.embedded.avnet.com/?link=tools/scotty/README.html
Project-URL: SimpleCore Documentation, https://simple.embedded.avnet.com/
Project-URL: Source Code, https://github.com/avnet-embedded/simplecore-tools/tree/scarthgap/scotty
License-File: LICENSE
Requires-Dist: jsonpath-ng~=1.7
Requires-Dist: requests~=2.32
Dynamic: author
Dynamic: description
Dynamic: description-content-type
Dynamic: license
Dynamic: project-url
Dynamic: requires-dist
Dynamic: summary
